pysignature/detect.py
pysignature/export.py
pysignature/models/__init__.py
pysignature/models/common.py
pysignature/models/experimental.py
pysignature/models/yolo.py
pysignature/utils/__init__.py
pysignature/utils/activations.py
pysignature/utils/augmentations.py
pysignature/utils/autoanchor.py
pysignature/utils/autobatch.py
pysignature/utils/callbacks.py
pysignature/utils/dataloaders.py
pysignature/utils/downloads.py
pysignature/utils/general.py
pysignature/utils/loss.py
pysignature/utils/metrics.py
pysignature/utils/plots.py
pysignature/utils/torch_utils.py
pysignature/utils/triton.py
signatureLens/detect.py
signatureLens/export.py
signatureLens/models/__init__.py
signatureLens/models/common.py
signatureLens/models/experimental.py
signatureLens/models/yolo.py
signatureLens/utils/__init__.py
signatureLens/utils/activations.py
signatureLens/utils/augmentations.py
signatureLens/utils/autoanchor.py
signatureLens/utils/autobatch.py
signatureLens/utils/callbacks.py
signatureLens/utils/dataloaders.py
signatureLens/utils/downloads.py
signatureLens/utils/general.py
signatureLens/utils/loss.py
signatureLens/utils/metrics.py
signatureLens/utils/plots.py
signatureLens/utils/torch_utils.py
signatureLens/utils/triton.py
signature_lens-0.1.0.dist-info/LICENSE
signature_lens-0.1.0.dist-info/METADATA
signature_lens-0.1.0.dist-info/WHEEL
signature_lens-0.1.0.dist-info/top_level.txt
signature_lens-0.1.0.dist-info/RECORD
